nsface/__init__.py
nsface/bbox_anchor.py
nsface/eval_WF.sh
nsface/eval_widerface.py
nsface/get_config.py
nsface/get_widerface_txt.py
nsface/inference_example_v1.0.31.ipynb
nsface/main_image.ipynb
nsface/onnx2trt.py
nsface/plot_prcurve.ipynb
nsface/print_info.py
nsface/readme.md
nsface/speed_calc.ipynb
nsface/.ipynb_checkpoints/Untitled-checkpoint.ipynb
nsface/.ipynb_checkpoints/Untitled1-checkpoint.ipynb
nsface/.ipynb_checkpoints/export_onnx_retina-checkpoint.ipynb
nsface/.ipynb_checkpoints/face_detector_test-checkpoint.ipynb
nsface/.ipynb_checkpoints/get_GenderAge-checkpoint.ipynb
nsface/.ipynb_checkpoints/get_landmark-checkpoint.ipynb
nsface/.ipynb_checkpoints/inference_example_v1.0.31-checkpoint.ipynb
nsface/.ipynb_checkpoints/main_image-checkpoint.ipynb
nsface/.ipynb_checkpoints/main_video-checkpoint.ipynb
nsface/.ipynb_checkpoints/plot_prcurve-checkpoint.ipynb
nsface/.ipynb_checkpoints/pred_to_txt-checkpoint.ipynb
nsface/.ipynb_checkpoints/print_info-checkpoint.py
nsface/.ipynb_checkpoints/ref_ori-checkpoint.png
nsface/.ipynb_checkpoints/speed_calc-checkpoint.ipynb
nsface/.ipynb_checkpoints/test2-checkpoint.jpg
nsface/.ipynb_checkpoints/test3-checkpoint.jpg
nsface/.ipynb_checkpoints/test_3ddfa-checkpoint.jpg
nsface/.ipynb_checkpoints/test_3ddfa_result-checkpoint.jpg
nsface/.ipynb_checkpoints/test_Retina_torch-checkpoint.ipynb
nsface/.ipynb_checkpoints/test_Retina_torch_pth-checkpoint.ipynb
nsface/.ipynb_checkpoints/test_Retina_useVinopy-checkpoint.ipynb
nsface/.ipynb_checkpoints/test_arcface_onnx-checkpoint.ipynb
nsface/.ipynb_checkpoints/test_crop-checkpoint.jpg
nsface/.ipynb_checkpoints/test_load-checkpoint.ipynb
nsface/.ipynb_checkpoints/test_mxnet-checkpoint.ipynb
nsface/.ipynb_checkpoints/test_onnx-checkpoint.ipynb
nsface/.ipynb_checkpoints/test_retina-checkpoint.ipynb
nsface/.ipynb_checkpoints/test_retina_getout-checkpoint.ipynb
nsface/.ipynb_checkpoints/test_tinaFace-checkpoint.ipynb
nsface/.ipynb_checkpoints/test_tinaface-checkpoint.ipynb
nsface_python-1.1.78.dist-info/METADATA
nsface_python-1.1.78.dist-info/WHEEL
nsface_python-1.1.78.dist-info/entry_points.txt
nsface_python-1.1.78.dist-info/top_level.txt
nsface_python-1.1.78.dist-info/RECORD
